Workbook

Sheet Stake Raw
C1: Printed: 2020-07-04 01:33:22 (UTC) | P1: Page 1 of | S1: 1
I4: Order Transactions Report
H6: Account #: STNR000103, Symbol: All
H8: Date Range: 2017-06-01 - 2020-07-04
B10: Order # | D10: Date/Time | F10: Status | J10: Order Type | K10: Side | L10: Symbol | M10: Qty | N10: Price | O10: Cum Qty | Q10: Leaves Qty
B11: GFPG003530 | D11: 2019-06-17T13:31:50.000Z | F11: PARTIALLY_FILLED | J11: MKT | K11: B | L11: BRK.B | M11: 9 | N11: $ 205.31 | O11: 9 | Q11: 0.739681
B12: GFPG003530 | D12: 2019-06-17T13:31:51.013Z | F12: FILLED | J12: MKT | K12: B | L12: BRK.B | M12: 0.81510885 | N12: $ 205.31 | O12: 9.81510885 | Q12: 0
B13: HCTB000014 | D13: 2020-03-02T14:34:17.437Z | F13: PARTIALLY_FILLED | J13: MKT | K13: S | L13: BRK.B | M13: 9 | N13: $ 207.89 | O13: 9 | Q13: 0.81510885
B14: HCTB000014 | D14: 2020-03-02T14:34:18.922Z | F14: FILLED | J14: MKT | K14: S | L14: BRK.B | M14: 0.81510885 | N14: $ 207.89 | O14: 9.81510885 | Q14: 0
B15: HFMP023789 | D15: 2020-06-16T13:30:09.920Z | F15: PARTIALLY_FILLED | J15: MKT | K15: B | L15: MSFT | M15: 5 | N15: $ 192.88 | O15: 5 | Q15: 0.38514492
B16: HFMP023789 | D16: 2020-06-16T13:31:10.483Z | F16: FILLED | J16: MKT | K16: B | L16: MSFT | M16: 0.39407922 | N16: $ 192.88 | O16: 5.39407922 | Q16: 0
B17: HFGQ023768 | D17: 2020-06-16T13:31:58.020Z | F17: FILLED | J17: MKT | K17: B | L17: AMZN | M17: 0.3840821 | N17: $ 2,603.61 | O17: 0.3840821 | Q17: 0
B18: HFXC039231 | D18: 2020-06-29T14:39:01.530Z | F18: PARTIALLY_FILLED | J18: MKT | K18: B | L18: FB | M18: 18 | N18: $ 215.29 | O18: 18 | Q18: 0.57959032
B19: HFXC039231 | D19: 2020-06-29T14:39:01.743Z | F19: FILLED | J19: MKT | K19: B | L19: FB | M19: 0.57963676 | N19: $ 215.29 | O19: 18.57963676 | Q19: 0
B20: HFZU038461 | D20: 2020-06-29T14:46:20.750Z | F20: PARTIALLY_FILLED | J20: MKT | K20: B | L20: TSLA | M20: 4 | N20: $ 983.49 | O20: 4 | Q20: 0.88353719
B21: HFZU038461 | D21: 2020-06-29T14:46:20.951Z | F21: FILLED | J21: MKT | K21: B | L21: TSLA | M21: 0.88353719 | N21: $ 983.49 | O21: 4.88353719 | Q21: 0
... B25: HGWZ001691 | D25: 2020-07-02T14:07:12.942Z | F25: FILLED | J25: MKT | K25: S | L25: FB | M25: 0.57963676 | N25: $ 234.92 | O25: 18.57963676 | Q25: 0
C26: You expressly acknowledge and agree that the DriveWealth Platforms and Related Services provided by us are on an ��as is�� basis, and that you use such DriveWealth Platforms and Related Services at your sole risk. Neither we nor our Third Party Providers will have any responsibility to maintain the DriveWealth Platforms and Related Services or to supply any corrections, updates or releases concerning the DriveWealth Platforms and Related Services

Sheet Investment Properties Summary
B4: 3/116 Mount Street, Coogee NSW 2034
B6: Updated on: 26/01/2026
B7: Loan | C7: Value | D7: Interest | E7: Repayment | F7: Expiry
B8: STG S212 669 298 400 V PI (offseting) | C8: 783854.3 | D8: 0.0539 | E8: 4517
B9: S212 669 298 401 V PI | C9: 112233.14 | D9: 0.0539 | E9: 647
C10: =SUBTOTAL(109,Table6[Value]) -> 896087.44 | E10: =SUBTOTAL(109,Table6[Repayment]) -> 5164
B13: Offset | C13: 21068.5
B14: Market Value (realestate) | C14: 1430000 | D14: (realstate)
B15: LVR | C15: =Table6[[#Totals],[Value]]/C14 -> 0.62663457
B16: RY Market Value | C16: =C24/C14 -> 0
B17: RY Load | C17: =C24/Table6[[#Totals],[Value]] -> 0
B18: Equity | C18: =C14-Table6[[#Totals],[Value]] -> 533912.56
B19: Forecasted Yearly CG % | C19: 0.07
B20: Forecasted Yearly CG | C20: =C14*C19 -> 100100
B22: Updated on: 20/4/2024
B23: Item | C23: Annually | D23: Monthly | E23: Weekly
B24: Rent | C24: =0*52 -> 0 | D24: =C24/12 -> 0 | E24: =Table10[[#This Row],[Annually]]/52 -> 0
B25: Council/Water rates/Internet | C25: =('Investment Properties Ongoing'!E7*4) + ('Investment Properties Ongoing'!E8*4) -> 9512.72 | D25: =C25/12 -> 792.72667 | E25: =C25/52 -> 182.93692
B26: Strata | C26: ='Investment Properties Ongoing'!E9*4 -> 5097.8 | D26: =C26/12 -> 424.81667 | E26: =C26/52 -> 98.034615
B27: Expenses/Repairs
B28: Agency Fee % | C28: 0
B29: Agency Fee $ | C29: =C24*C28 -> 0 | D29: =C29/12 -> 0 | E29: =C29/52 -> 0
B30: Repayment | C30: =Table6[[#Totals],[Repayment]]*12 -> 61968 | D30: =C30/12 -> 5164 | E30: =C30/52 -> 1191.6923
B31: Total Expenses | C31: =SUM(C25,C26,C27,C29,C30) -> 76578.52 | D31: =Table10[[#This Row],[Annually]]/12 -> 6381.5433 | E31: =Table10[[#This Row],[Annually]]/52 -> 1472.6638
B32: Out Off Pocket | C32: =C24-C31 -> -76578.52 | D32: =C32/12 -> -6381.5433 | E32: =C32/52 -> -1472.6638
B36: 10 Arura Street, Mansfield QLD 4122
B37: Updated on: 26/01/2026
B39: Loan | C39: Value | D39: Interest | E39: Repayment | F39: Expiry
B40: STG S212 669 139 100 V IO (offseting?) | C40: 620000 | D40: 0.0584 | E40: 3075.2 | F40: 47198
B41: STG S212 669 139 101 V IO (equity release) (offseting this one I think) | C41: 35000 | D41: 0.0584 | E41: 173.6 | F41: 47198
C42: =SUBTOTAL(109,Table612[Value]) -> 655000 | E42: =SUBTOTAL(109,Table612[Repayment]) -> 3248.8
B45: Offset (acc. 1260 0659) | C45: 40268.19
B46: Market Value 20/4/2024 (realestate) | C46: 1380000 | D46: (realstate)
B47: LVR | C47: =Table612[[#Totals],[Value]]/C46 -> 0.47463768
B48: RY Market Value | C48: =C56/C46 -> 0.026753623
B49: RY Load | C49: =C56/Table612[[#Totals],[Value]] -> 0.056366412
B50: Equity | C50: =C46-Table612[[#Totals],[Value]] -> 725000
B51: Forecasted Yearly CG % | C51: 0.07
B52: Forecasted Yearly CG | C52: =C46*C51 -> 96600
B54: Updated on: To update
B55: Item | C55: Annually | D55: Monthly | E55: Weekly
B56: Rent | C56: =710*52 -> 36920 | D56: =C56/12 -> 3076.6667 | E56: =Table1014[[#This Row],[Annually]]/52 -> 710
B57: Council/Water rates/Internet | C57: =('Investment Properties Ongoing'!E18*4) +('Investment Properties Ongoing'!E19*4) -> 3943.12 | D57: =C57/12 -> 328.59333 | E57: =C57/52 -> 75.829231
B58: Strata | C58: ='Investment Properties Ongoing'!E36*4 -> 0 | D58: =C58/12 -> 0 | E58: =C58/52 -> 0
B59: Expenses/Repairs | C59: =C46*0.005 -> 6900
B60: Agency Fee % | C60: 0.0825
B61: Agency Fee $ | C61: =C56*C60 -> 3045.9 | D61: =C61/12 -> 253.825 | E61: =C61/52 -> 58.575
B62: Repayment | C62: =Table612[[#Totals],[Repayment]]*12 -> 38985.6 | D62: =C62/12 -> 3248.8 | E62: =C62/52 -> 749.72308
B63: Total Expenses | C63: =SUM(C57,C58,C59,C61,C62) -> 52874.62 | D63: =Table1014[[#This Row],[Annually]]/12 -> 4406.2183 | E63: =Table1014[[#This Row],[Annually]]/52 -> 1016.8196
B64: Out Off Pocket | C64: =C56-C63 -> -15954.62 | D64: =C64/12 -> -1329.5517 | E64: =C64/52 -> -306.81962 | J64: =Table1014[[#This Row],[Monthly]]/2 -> -664.77583 | K64: Cost per person per month
B67: 23 St. Huberts, Carnegie VIC 3163
B68: Updated on: 26/01/2026
B69: Discount: 1.84%
B70: Loan | C70: Value | D70: Interest | E70: Repayment | F70: Expiry
B71: CBA 88255 2754 V IO (offsetting) | C71: 794790 | D71: 0.0595 | E71: 3359.51 | F71: 46411
C72: =SUBTOTAL(109,Table61216[Value]) -> 794790 | E72: =SUBTOTAL(109,Table61216[Repayment]) -> 3359.51
B74: Offset | C74: 141675.72
B75: Market Value 20/4/2024 (realestate) | C75: 934000 | D75: (realstate)
B76: LVR | C76: =Table61216[[#Totals],[Value]]/C75 -> 0.85095289
B77: RY Market Value | C77: =C85/C75 -> 0.038415418
B78: RY Load | C78: =C85/Table61216[[#Totals],[Value]] -> 0.045144
B79: Equity | C79: =C75-Table61216[[#Totals],[Value]] -> 139210
B80: Forecasted Yearly CG % | C80: 0.07
B81: Forecasted Yearly CG | C81: =C75*C80 -> 65380
B83: Updated on: To update
B84: Item | C84: Annually | D84: Monthly | E84: Weekly
B85: Rent | C85: =690*52 -> 35880 | D85: =C85/12 -> 2990 | E85: =Table101418[[#This Row],[Annually]]/52 -> 690
B86: Council/Water rates/Internet | C86: =SUM(Table138[Amount]) -> 1668.4375 | D86: =C86/12 -> 139.03646 | E86: =C86/52 -> 32.085337
B87: Strata | C87: ='Investment Properties Ongoing'!E65*4 -> 0 | D87: =C87/12 -> 0 | E87: =C87/52 -> 0
B88: Expenses/Repairs | C88: =C75*0.005 -> 4670
B89: Agency Fee % | C89: 0.075
B90: Agency Fee $ | C90: =C85*C89 -> 2691 | D90: =C90/12 -> 224.25 | E90: =C90/52 -> 51.75
B91: Repayment | C91: =Table61216[[#Totals],[Repayment]]*12 -> 40314.12 | D91: =C91/12 -> 3359.51 | E91: =C91/52 -> 775.27154
B92: Total Expenses | C92: =SUM(C86,C87,C88,C90,C91) -> 49343.558 | D92: =Table101418[[#This Row],[Annually]]/12 -> 4111.9631 | E92: =Table101418[[#This Row],[Annually]]/52 -> 948.91457
B93: Out Off Pocket | C93: =C85-C92 -> -13463.558 | D93: =C93/12 -> -1121.9631 | E93: =C93/52 -> -258.91457
B97: Totals - Annual - Home + Inv. properties
B99: Total Repayments | C99: =SUM(C30,C62,C91) -> 141267.72
B100: Total Rents | C100: =SUM(C24,C56,C85) -> 72800
B101: Total Expenses | C101: =SUM(C31,C63,C92) - C99 -> 37528.978
B102: Total Forcasted Yearly CG | C102: =SUM(C20,C52,C81) -> 262080
B103: Total Out Off Pocket | C103: =C100-SUM(C99,C101) -> -105996.7
B106: Totals - Annual - ONLY Inv. properties
B108: Total Repayments | C108: =SUM(C62,C91) -> 79299.72
B109: Total Rents | C109: =SUM(C56,C85) -> 72800
B110: Total Expenses | C110: =SUM(C63,C92) - C108 -> 22918.457
B111: Total Forcasted Yearly CG | C111: =SUM(C52,C81) -> 161980
B112: Total Out Off Pocket | C112: =C109-SUM(C108,C110) -> -29418.177
B115: Totals - Annual - Home (Mount st)
B117: Total Repayments | C117: =C30 -> 61968
B118: Total Rents | C118: 0
B119: Total Expenses | C119: =C31-C117 -> 14610.52
B120: Total Forcasted Yearly CG | C120: =C20 -> 100100
B121: Total Out Off Pocket | C121: =C118-SUM(C117,C119) -> -76578.52
B124: Total Owned | C124: =SUM(C40:C41,C8:C9,C71) -> 2345877.4
B126: Total Property Value | C126: =C75+C46+C14 -> 3744000
B128: Total Equity | C128: =C126-C124 -> 1398122.6
B130: Total Offset Account | C130: =C74+C45+C13 -> 203012.41

Sheet Summary v2
B2: Property Portfolio Summary
B3: Blue = manual input • Black = calculated • Green = totals
B4: Last updated: | C4: 26/01/2026
B6: INPUTS | C6: Home (Coogee) | D6: Investment (Mansfield) | E6: Investment (Carnegie)
B7: Address | C7: 3/116 Mount Street, Coogee NSW 2034 | D7: 10 Arura Street, Mansfield QLD 4122 | E7: lot 2 23 St. Huberts, Carnegie VIC 3163
B8: Type | C8: Home | D8: Investment | E8: Investment
B9: Market Value | C9: 1440000 | D9: 1430000 | E9: 956000
B10: Bank | C10: St George | D10: St George | E10: CBA
B11: Loan 1 balance | C11: 783854.3 | D11: 620000 | E11: 794790
B12: Loan 1 type | C12: OO P&I Var | D12: Inv IO Var | E12: Inv IO Var
B13: Loan 1 interest rate | C13: 0.0539 | D13: 0.0634 | E13: 0.0645
B14: Loan 1 repayment (monthly) | C14: 4517 | D14: 3296.02 | E14: 3359.51
B15: Loan 1 IO expiry | D15: 47198 | E15: 46411
B16: Loan 2 balance | C16: 112233.14 | D16: 35000 | E16: 0
B17: Loan 2 type | C17: OO P&I Var | D17: Inv IO Var | E17: Inv IO Var
B18: Loan 2 interest rate | C18: 0.0539 | D18: 0.0634 | E18: 0
B19: Loan 2 repayment (monthly) | C19: 647 | D19: 185.06 | E19: 0
B20: Loan 1 IO expiry | D20: 47198
B21: Offset balance | C21: 21068.5 | D21: 40749.49 | E21: 139316.79
B22: Weekly rent | C22: 0 | D22: 740 | E22: =2998/4.3333 -> 691.85148
B23: Repairs buffer (% of value) | C23: 0.05 | D23: 0.05 | E23: 0.05
B24: Agency fee % | C24: 0 | D24: 0.0825 | E24: 0.075
B25: Forecasted CG % | C25: 0.07 | D25: 0.07 | E25: 0.07
B27: CALCULATIONS
B28: Position
B29: Total loan | C29: =C11+C16 -> 896087.44 | D29: =D11+D16 -> 655000 | E29: =E11+E16 -> 794790
B30: LVR | C30: =C29/C9 -> 0.62228294 | D30: =D29/D9 -> 0.45804196 | E30: =E29/E9 -> 0.83137029
B31: Equity | C31: =C9-C29 -> 543912.56 | D31: =D9-D29 -> 775000 | E31: =E9-E29 -> 161210
B32: Effective loan (net of offset) | C32: =C29-C21 -> 875018.94 | D32: =D29-D21 -> 614250.51 | E32: =E29-E21 -> 655473.21
B33: Forecasted capital gain ($/yr) | C33: =C9*C25 -> 100800 | D33: =D9*D25 -> 100100 | E33: =E9*E25 -> 66920
B35: Income & Expenses (annual)
B36: Rent | C36: =C22*52 -> 0 | D36: =D22*52 -> 38480 | E36: =E22*52 -> 35976.277
B37: Council / Water / Internet | C37: =SUM('Investment Properties Ongoing'!E7,'Investment Properties Ongoing'!E8,'Investment Properties Ongoing'!E11,'Investment Properties Ongoing'!E10) -> 3034.7 | D37: =('Investment Properties Ongoing'!E18*4) +('Investment Properties Ongoing'!E19*4) -> 3943.12 | E37: =SUM(Table138[Amount]) -> 1668.4375
B38: Strata | C38: ='Investment Properties Ongoing'!E9 -> 1274.45 | E38: ='Investment Properties Ongoing'!E28 -> 249.5
B39: Repairs buffer | C39: =C9*C23/10 -> 7200 | D39: =D9*D23/10 -> 7150 | E39: =E9*E23/10 -> 4780
B40: Agency fee | C40: =C36*C24 -> 0 | D40: =D36*D24 -> 3174.6 | E40: =E36*E24 -> 2698.2208
B41: Loan repayments | C41: =(C14+C19)*12 -> 61968 | D41: =(D14+D19)*12 -> 41772.96 | E41: =(E14+E19)*12 -> 40314.12
B42: Total expenses | C42: =SUM(C37:C41) -> 73477.15 | D42: =SUM(D37:D41) -> 56040.68 | E42: =SUM(E37:E41) -> 49710.278
B43: Out-of-pocket (annual) | C43: =C36-C42 -> -73477.15 | D43: =D36-D42 -> -17560.68 | E43: =E36-E42 -> -13734.002
B44: Out-of-pocket (monthly) | C44: =C43/12 -> -6123.0958 | D44: =D43/12 -> -1463.39 | E44: =E43/12 -> -1144.5001
B45: Out-of-pocket (weekly) | C45: =C43/52 -> -1413.0221 | D45: =D43/52 -> -337.70538 | E45: =E43/52 -> -264.11541
B47: Yields
B48: Gross rental yield | C48: =IFERROR(C36/C9,0) -> 0 | D48: =IFERROR(D36/D9,0) -> 0.026909091 | E48: =IFERROR(E36/E9,0) -> 0.037632089
B49: Net yield (pre-repayments) | C49: =IFERROR((C36-C37-C38-C39-C40)/C9,0) -> -0.0079924653 | D49: =IFERROR((D36-D37-D38-D39-D40)/D9,0) -> 0.016931664 | E49: =IFERROR((E36-E37-E38-E39-E40)/E9,0) -> 0.027803471
B50: Total return (yield + CG) | C50: =C49+C25 -> 0.062007535 | D50: =D49+D25 -> 0.086931664 | E50: =E49+E25 -> 0.097803471
B52: PORTFOLIO TOTALS | C52: All Properties | D52: Investments Only | E52: Home Only
B53: Total property value | C53: =SUM(C9:E9) -> 3826000 | D53: =SUM(D9:E9) -> 2386000 | E53: =C9 -> 1440000
B54: Total loans | C54: =SUM(C29:E29) -> 2345877.4 | D54: =SUM(D29:E29) -> 1449790 | E54: =C29 -> 896087.44
B55: Total equity | C55: =C53-C54 -> 1480122.6 | D55: =D53-D54 -> 936210 | E55: =E53-E54 -> 543912.56
B56: Portfolio LVR | C56: =C54/C53 -> 0.61314099 | D56: =D54/D53 -> 0.60762364 | E56: =E54/E53 -> 0.62228294
B57: Total offset | C57: =SUM(C21:E21) -> 201134.78 | D57: =SUM(D21:E21) -> 180066.28 | E57: =C21 -> 21068.5
B58: Effective loan (net of offset) | C58: =SUM(C32:E32) -> 2144742.7 | D58: =SUM(D32:E32) -> 1269723.7 | E58: =C32 -> 875018.94
B60: Annual rent | C60: =SUM(C36:E36) -> 74456.277 | D60: =SUM(D36:E36) -> 74456.277 | E60: =C36 -> 0
B61: Annual repayments | C61: =SUM(C41:E41) -> 144055.08 | D61: =SUM(D41:E41) -> 82087.08 | E61: =C41 -> 61968
B62: Annual other expenses | C62: =SUM(C42:E42)-C61 -> 35173.028 | D62: =SUM(D42:E42)-D61 -> 23663.878 | E62: =C42-C41 -> 11509.15
B63: Out-of-pocket (annual) | C63: =SUM(C43:E43) -> -104771.83 | D63: =SUM(D43:E43) -> -31294.682 | E63: =C43 -> -73477.15
B64: Out-of-pocket (monthly) | C64: =C63/12 -> -8730.986 | D64: =D63/12 -> -2607.8901 | E64: =E63/12 -> -6123.0958
B65: Out-of-pocket (weekly) | C65: =C63/52 -> -2014.8429 | D65: =D63/52 -> -601.8208 | E65: =E63/52 -> -1413.0221
B67: Forecasted capital gain ($/yr) | C67: =SUM(C33:E33) -> 267820 | D67: =SUM(D33:E33) -> 167020 | E67: =C33 -> 100800
B68: Net position (CG − out-of-pocket) | C68: =C67+C63 -> 163048.17 | D68: =D67+D63 -> 135725.32 | E68: =E67+E63 -> 27322.85

Sheet Investment Properties Ongoing
B2: Investment Properties
B4: 3/116 Mount Street, Coogee NSW 2034
B6: Description | C6: Payment Method | D6: Notifications go to | E6: Amount | F6: Last Payment | G6: Next Payment | H6: Descriptions | I6: Login | J6: How to check
B7: Randwick Council | C7: Direct Debit ?? | D7: gabrielandarina@gmail.com | E7: 478.5 | F7: 46071 | I7: not availiable | J7: email from: council@randwick.nsw.gov.au to checl instalments and direct debit is set on Our Acc. Search for RANDWICK CITY CO
B8: Sydney Water | C8: Direct Debit | D8: gabrielandarina@gmail.com | E8: 1899.68 | F8: 46052 | I8: pass:Watergab1
B9: Strata Levis | C9: Manual (offset) | D9: gabrielandarina@gmail.com | E9: 1274.45 | F9: 46082 | J9: search for:strata
B10: Red energy (Eletricity) | C10: Direct Debit | D10: gabriel.serra@outlook.com.au | E10: 371.52 | F10: 46024 | I10: pass:AglMount15
B11: Aussie Broadband (internet) | C11: Direct Debit | D11: gabrielandarina@gmail.com | E11: =95*3 -> 285 | F11: 46047 | I11: gabrielponde/TpGgaser12
B12: TOTAL | E12: =SUM(Table1[Amount]) -> 4309.15
B15: 10 Arura Street, Mansfield QLD 4122
B17: Description | C17: Payment Method | D17: Notifications go to | E17: Amount | F17: Last Payment | G17: Next Payment | H17: Descriptions | I17: Login | J17: How to check
B18: Brisbane Council | C18: Bpay View | D18: gabrielandarina@gmail.com | E18: 776.05 | F18: 45875 | H18: Belle property to pay. | J18: searh for: Bcc rates
B19: Urban Util Water | C19: Direct Debit (offset) | D19: gabrielandarina@gmail.com | E19: =353.66-143.93 -> 209.73 | F19: 46022 | H19: Belle property to pay. Sewage and base wter. Tenants pay usage. | I19: gabrielandarina@gmail.com.au | J19: search: URBAN UTILITIES
B20: Land tax | D20: arina.cociuban@gmail.com | E20: =1000/4 -> 250 | F20: 45839 | H20: notification ari receives
B21: TOTAL | E21: =SUM(Table13[Amount]) -> 1235.78
B23: St Hubert, Carnegie VIC ????
B25: Description | C25: Payment Method | D25: Notifications go to | E25: Amount | F25: Last Payment | G25: Next Payment | H25: Descriptions | I25: Login | J25: How to check
B26: GLEN EIRA COUNCIL | C26: Bpay View | D26: gabrielandarina@gmail.com | E26: =1654.15/4 -> 413.5375 | F26: 45839 | H26: Issues with Gary Peer paying in time
B27: South East Water | C27: Direct Debit (offset) | D27: gabrielandarina@gmail.com | E27: =691.6/4 -> 172.9 | F27: 45839 | H27: Gary Peero to pay.
B28: Body corgporate Fees | C28: Direct Debit (offset) | D28: gabrielandarina@gmail.com | E28: =998/4 -> 249.5 | F28: 45108 | H28: Total $958 per annum - to pay to Sabrina Sestito
B29: Land tax | D29: gabrielandarina@gmail.com | E29: =3330/4 -> 832.5 | F29: 45108 | H29: Total $715 per annum - paid in Sept to State Revenue
B31: TOTAL | E31: =SUM(E26:E29) -> 1668.4375
B48: 10 Arura Street, Mansfield QLD 4122
B49: Updated on: 28/08/2021
B50: Discount: 1.84%
G51: Expiry
B52: Variable Loan 1 | D52: 12763.58 | F52: 0.0329 | G52: NA
B53: PI Fixed Loan | D53: 128135.49 | F53: 0.0259 | G53: 45316
B54: IO Fixed Loan | D54: 407379 | F54: 0.0269 | G54: 45313
B55: Total | D55: =D52+D54+D53 -> 548278.07
B57: Market Value (CBA 30/3/21) | D57: 705000
B58: LVR | D58: =(D55)/D57 -> 0.77769939
B59: Equity | D59: =D57-D55 -> 156721.93
D61: Annually | F61: Monthly
B62: Rent | D62: =485*52 -> 25220 | F62: =D62/12 -> 2101.6667
B63: Council/Water rates | D63: =(610+137+60)*4 -> 3228 | F63: =D63/12 -> 269
B64: Expenses/Repairs
B65: Agency Fee % | D65: 0.0775
B66: Agency Fee $ | D66: =D62*D65 -> 1954.55 | F66: =D66/12 -> 162.87917
B67: Repayment Fixed | D67: =(544+840.65)*12 -> 16615.8 | F67: =D67/12 -> 1384.65
B68: Repayment Varible | D68: =(60)*12 -> 720
B69: Repayment Total | D69: =D67+D68 -> 17335.8
B70: Out Off Pocket Repayment | D70: =D62-D63-D66-D69 -> 2701.65 | F70: =D70/12 -> 225.1375
B71: Offset Account | D71: 10155.56
B73: Totals
B75: Total Off Pocket Repayments | D75: =D44+D70 -> 2701.65
B76: Total Offset Accounts | D76: =D45+D71 -> 10155.56

Sheet Super
B3: Gabriel Supper - HostPlus
B6: Date | C6: Investment Option | D6: Unit Price | E6: Units | F6: Value
B7: 44172 | C7: Diversified FixedInt | D7: 2.0156 | E7: 30312.839 | F7: =Table14[[#This Row],[Unit Price]]*Table14[[#This Row],[Units]] -> 61098.559 | H7: TO CHANGE
F8: =Table14[[#This Row],[Unit Price]]*Table14[[#This Row],[Units]] -> 0
F9: =Table14[[#This Row],[Unit Price]]*Table14[[#This Row],[Units]] -> 0
F10: =Table14[[#This Row],[Unit Price]]*Table14[[#This Row],[Units]] -> 0
F11: =Table14[[#This Row],[Unit Price]]*Table14[[#This Row],[Units]] -> 0
F12: =Table14[[#This Row],[Unit Price]]*Table14[[#This Row],[Units]] -> 0
F13: =Table14[[#This Row],[Unit Price]]*Table14[[#This Row],[Units]] -> 0
F14: =Table14[[#This Row],[Unit Price]]*Table14[[#This Row],[Units]] -> 0
F15: =Table14[[#This Row],[Unit Price]]*Table14[[#This Row],[Units]] -> 0
B17: Insurance
B18: Total permanent disability | C18: 229,160.00
B19: Income Protection | C19: 0 | D19: TODO
B23: Arina Supper - AU Super
B26: Date | C26: Investment Option | D26: Unit Price | E26: Units | F26: Value
B27: 44172 | C27: Diversified Fixed Interes | F27: 161500
F28: =Table145[[#This Row],[Unit Price]]*Table145[[#This Row],[Units]] -> 0
F29: =Table145[[#This Row],[Unit Price]]*Table145[[#This Row],[Units]] -> 0
F30: =Table145[[#This Row],[Unit Price]]*Table145[[#This Row],[Units]] -> 0
F31: =Table145[[#This Row],[Unit Price]]*Table145[[#This Row],[Units]] -> 0
F32: =Table145[[#This Row],[Unit Price]]*Table145[[#This Row],[Units]] -> 0
F33: =Table145[[#This Row],[Unit Price]]*Table145[[#This Row],[Units]] -> 0
F34: =Table145[[#This Row],[Unit Price]]*Table145[[#This Row],[Units]] -> 0
F35: =Table145[[#This Row],[Unit Price]]*Table145[[#This Row],[Units]] -> 0
B38: Insurance
B39: Total permanent disability | C39: 193000
B40: Income Protection | C40: 5000

Sheet Summary v3
B2: Property Portfolio Summary
B3: Blue = manual input • Black = calculated • Green = totals
B4: Last updated: | C4: 26/01/2026
B6: INPUTS | C6: Home (Coogee) | D6: Investment (Mansfield) | E6: Investment (Carnegie)
B7: Address | C7: 3/116 Mount Street, Coogee NSW 2034 | D7: 10 Arura Street, Mansfield QLD 4122 | E7: lot 2 23 St. Huberts, Carnegie VIC 3163
B8: Type | C8: Home | D8: Investment | E8: Investment
B9: Market Value | C9: 1440000 | D9: 1430000 | E9: 956000
B10: Bank | C10: St George | D10: St George | E10: CBA
B11: Loan 1 balance | C11: 783854.3 | D11: 620000 | E11: 794790
B12: Loan 1 type | C12: OO P&I Var | D12: Inv IO Var | E12: Inv IO Var
B13: Loan 1 interest rate | C13: 0.0539 | D13: 0.0634 | E13: 0.0645
B14: Loan 1 repayment (monthly) | C14: 4517 | D14: 3296.02 | E14: 3359.51
B15: Loan 1 IO expiry | D15: 47198 | E15: 46411
B16: Loan 2 balance | C16: 112233.14 | D16: 35000 | E16: 0
B17: Loan 2 type | C17: OO P&I Var | D17: Inv IO Var | E17: Inv IO Var
B18: Loan 2 interest rate | C18: 0.0539 | D18: 0.0634 | E18: 0
B19: Loan 2 repayment (monthly) | C19: 647 | D19: 185.06 | E19: 0
B20: Loan 2 IO expiry | D20: 47198
B21: Offset balance | C21: 21068.5 | D21: 40749.49 | E21: 139316.79
B22: Weekly rent | C22: 0 | D22: 740 | E22: =2998/4.3333 -> 691.85148
B23: Repairs buffer (% of value) | C23: 0.05 | D23: 0.05 | E23: 0.05
B24: Agency fee % | C24: 0 | D24: 0.0825 | E24: 0.075
B25: Forecasted CG % | C25: 0.07 | D25: 0.07 | E25: 0.07
B27: INPUT ONGOING EXPENSES MONTLY | C27: Home (Coogee) | D27: Investment (Mansfield) | E27: Investment (Carnegie)
B28: Council rates (charged quarterly) | C28: =478.5/3 -> 159.5 | D28: =776.05/3 -> 258.68333 | E28: =442.45/3 -> 147.48333
B29: Council rates - notes | C29: Randwick Council — Direct Debit — gabrielandarina@gmail.com email from: council@randwick.nsw.gov.au LAST BILL: 28/02/2026 | D29: Brisbane Council — Bpay View — gabrielandarina@gmail.com Belle property to pay. search for: Brisbane City Council LAST BILL: 06/02/2026 | E29: Glen Eira Council — Bpay View — gabrielandarina@gmail.com Gary Peer to pay Issues with Gary Peer paying in time LAST BILL: 31/05/2026
B30: Water | C30: 1899.68 | D30: =353.66-143.93 -> 209.73 | E30: =691.6/4 -> 172.9 | F30: to update the below
B31: Water - notes | C31: Sydney Water — Direct Debit — gabrielandarina@gmail.com — pass: Watergab1 | D31: Urban Utilities — Direct Debit (offset) — gabrielandarina@gmail.com — Belle property to pay. Sewage and base water. Tenants pay usage. search: URBAN UTILITIES | E31: South East Water — Direct Debit (offset) — gabrielandarina@gmail.com — Gary Peer to pay
B32: Strata / Body Corporate | C32: 1274.45 | E32: =998/4 -> 249.5
B33: Strata / Body Corporate - notes | C33: Strata Levies — Manual (offset) — gabrielandarina@gmail.com — search for: strata | E33: Body Corporate — Direct Debit (offset) — gabrielandarina@gmail.com — Total $998/yr — to pay to Sabrina Sestito
B34: Electricity | C34: 371.52
B35: Electricity - notes | C35: Red Energy — Direct Debit — gabriel.serra@outlook.com.au — pass: AglMount15
B36: Internet | C36: =95*3 -> 285
B37: Internet - notes | C37: Aussie Broadband — Direct Debit — gabrielandarina@gmail.com — login: gabrielponde / TpGgaser12
B38: Land tax | D38: =1000/4 -> 250 | E38: =3330/4 -> 832.5
B39: Land tax - notes | D39: Land tax — arina.cociuban@gmail.com — notification ari receives | E39: Land tax — Total $3,330/yr — paid in Sept to State Revenue
B41: Subtotal (as billed) | C41: =C28+C30+C32+C34+C36+C38 -> 3990.15 | D41: =D28+D30+D32+D34+D36+D38 -> 718.41333 | E41: =E28+E30+E32+E34+E36+E38 -> 1402.3833
B42: Annualised total | C42: =C41 -> 3990.15 | D42: =D41*4 -> 2873.6533 | E42: =E41*4 -> 5609.5333
B45: CALCULATIONS
B46: Position
B47: Total loan | C47: =C11+C16 -> 896087.44 | D47: =D11+D16 -> 655000 | E47: =E11+E16 -> 794790
B48: LVR | C48: =C47/C9 -> 0.62228294 | D48: =D47/D9 -> 0.45804196 | E48: =E47/E9 -> 0.83137029
B49: Equity | C49: =C9-C47 -> 543912.56 | D49: =D9-D47 -> 775000 | E49: =E9-E47 -> 161210
B50: Effective loan (net of offset) | C50: =C47-C21 -> 875018.94 | D50: =D47-D21 -> 614250.51 | E50: =E47-E21 -> 655473.21
B51: Forecasted capital gain ($/yr) | C51: =C9*C25 -> 100800 | D51: =D9*D25 -> 100100 | E51: =E9*E25 -> 66920
B53: Income & Expenses (annual)
B54: Rent | C54: =C22*52 -> 0 | D54: =D22*52 -> 38480 | E54: =E22*52 -> 35976.277
B55: Council / Water / Internet | C55: =C28+C30+C34+C36 -> 2715.7 | D55: =(D28+D30)*4 -> 1873.6533 | E55: =E41 -> 1402.3833
B56: Strata | C56: =C32 -> 1274.45 | D56: 0 | E56: =E32 -> 249.5
B57: Repairs buffer | C57: =C9*C23/10 -> 7200 | D57: =D9*D23/10 -> 7150 | E57: =E9*E23/10 -> 4780
B58: Agency fee | C58: =C54*C24 -> 0 | D58: =D54*D24 -> 3174.6 | E58: =E54*E24 -> 2698.2208
B59: Loan repayments | C59: =(C14+C19)*12 -> 61968 | D59: =(D14+D19)*12 -> 41772.96 | E59: =(E14+E19)*12 -> 40314.12
B60: Total expenses | C60: =SUM(C55:C59) -> 73158.15 | D60: =SUM(D55:D59) -> 53971.213 | E60: =SUM(E55:E59) -> 49444.224
B61: Out-of-pocket (annual) | C61: =C54-C60 -> -73158.15 | D61: =D54-D60 -> -15491.213 | E61: =E54-E60 -> -13467.947
B62: Out-of-pocket (monthly) | C62: =C61/12 -> -6096.5125 | D62: =D61/12 -> -1290.9344 | E62: =E61/12 -> -1122.3289
B63: Out-of-pocket (weekly) | C63: =C61/52 -> -1406.8875 | D63: =D61/52 -> -297.90795 | E63: =E61/52 -> -258.99899
B65: Yields
B66: Gross rental yield | C66: =IFERROR(C54/C9,0) -> 0 | D66: =IFERROR(D54/D9,0) -> 0.026909091 | E66: =IFERROR(E54/E9,0) -> 0.037632089
B67: Net yield (pre-repayments) | C67: =IFERROR((C54-C55-C56-C57-C58)/C9,0) -> -0.0077709375 | D67: =IFERROR((D54-D55-D56-D57-D58)/D9,0) -> 0.018378844 | E67: =IFERROR((E54-E55-E56-E57-E58)/E9,0) -> 0.028081771
B68: Total return (yield + CG) | C68: =C67+C25 -> 0.062229063 | D68: =D67+D25 -> 0.088378844 | E68: =E67+E25 -> 0.098081771
B70: PORTFOLIO TOTALS | C70: All Properties | D70: Investments Only | E70: Home Only
B71: Total property value | C71: =SUM(C9:E9) -> 3826000 | D71: =SUM(D9:E9) -> 2386000 | E71: =C9 -> 1440000
B72: Total loans | C72: =SUM(C47:E47) -> 2345877.4 | D72: =SUM(D47:E47) -> 1449790 | E72: =C47 -> 896087.44
B73: Total equity | C73: =C71-C72 -> 1480122.6 | D73: =D71-D72 -> 936210 | E73: =E71-E72 -> 543912.56
B74: Portfolio LVR | C74: =C72/C71 -> 0.61314099 | D74: =D72/D71 -> 0.60762364 | E74: =E72/E71 -> 0.62228294
B75: Total offset | C75: =SUM(C21:E21) -> 201134.78 | D75: =SUM(D21:E21) -> 180066.28 | E75: =C21 -> 21068.5
B76: Effective loan (net of offset) | C76: =SUM(C50:E50) -> 2144742.7 | D76: =SUM(D50:E50) -> 1269723.7 | E76: =C50 -> 875018.94
B78: Annual rent | C78: =SUM(C54:E54) -> 74456.277 | D78: =SUM(D54:E54) -> 74456.277 | E78: =C54 -> 0
B79: Annual repayments | C79: =SUM(C59:E59) -> 144055.08 | D79: =SUM(D59:E59) -> 82087.08 | E79: =C59 -> 61968
B80: Annual other expenses | C80: =SUM(C60:E60)-C79 -> 32518.507 | D80: =SUM(D60:E60)-D79 -> 21328.357 | E80: =C60-C59 -> 11190.15
B81: Out-of-pocket (annual) | C81: =SUM(C61:E61) -> -102117.31 | D81: =SUM(D61:E61) -> -28959.161 | E81: =C61 -> -73158.15
B82: Out-of-pocket (monthly) | C82: =C81/12 -> -8509.7759 | D82: =D81/12 -> -2413.2634 | E82: =E81/12 -> -6096.5125
B83: Out-of-pocket (weekly) | C83: =C81/52 -> -1963.7944 | D83: =D81/52 -> -556.90694 | E83: =E81/52 -> -1406.8875
B85: Forecasted capital gain ($/yr) | C85: =SUM(C51:E51) -> 267820 | D85: =SUM(D51:E51) -> 167020 | E85: =C51 -> 100800
B86: Net position (CG − out-of-pocket) | C86: =C85+C81 -> 165702.69 | D86: =D85+D81 -> 138060.84 | E86: =E85+E81 -> 27641.85
